MANIFEST.in
README.rst
setup.py
jskom/__init__.py
jskom/__main__.py
jskom/version.py
jskom.egg-info/PKG-INFO
jskom.egg-info/SOURCES.txt
jskom.egg-info/dependency_links.txt
jskom.egg-info/not-zip-safe
jskom.egg-info/requires.txt
jskom.egg-info/top_level.txt
jskom/static/.gitignore
jskom/static/favicon.ico
jskom/static/style.css
jskom/static/app/jskom.HttpkomConnection.js
jskom/static/app/jskom.HttpkomConnection.js~
jskom/static/app/jskom.MembershipList.js
jskom/static/app/jskom.MembershipList.js~
jskom/static/app/jskom.MembershipListHandler.js
jskom/static/app/jskom.MembershipListHandler.js~
jskom/static/app/jskom.Reader.js
jskom/static/app/jskom.Reader.js~
jskom/static/app/jskom.connections.js
jskom/static/app/jskom.controllers.js
jskom/static/app/jskom.directives.js
jskom/static/app/jskom.filters.js
jskom/static/app/jskom.js
jskom/static/app/jskom.keybindings.js
jskom/static/app/jskom.services.js
jskom/static/app/jskom.templates.js
jskom/static/fonts/fontawesome/fontawesome-webfont.eot
jskom/static/fonts/fontawesome/fontawesome-webfont.svg
jskom/static/fonts/fontawesome/fontawesome-webfont.ttf
jskom/static/fonts/fontawesome/fontawesome-webfont.woff
jskom/static/fonts/foundicons/accessibility/accessibility_foundicons.eot
jskom/static/fonts/foundicons/accessibility/accessibility_foundicons.svg
jskom/static/fonts/foundicons/accessibility/accessibility_foundicons.ttf
jskom/static/fonts/foundicons/accessibility/accessibility_foundicons.woff
jskom/static/fonts/foundicons/general/general_foundicons.eot
jskom/static/fonts/foundicons/general/general_foundicons.svg
jskom/static/fonts/foundicons/general/general_foundicons.ttf
jskom/static/fonts/foundicons/general/general_foundicons.woff
jskom/static/fonts/foundicons/general_enclosed/general_enclosed_foundicons.eot
jskom/static/fonts/foundicons/general_enclosed/general_enclosed_foundicons.svg
jskom/static/fonts/foundicons/general_enclosed/general_enclosed_foundicons.ttf
jskom/static/fonts/foundicons/general_enclosed/general_enclosed_foundicons.woff
jskom/static/fonts/foundicons/social/social_foundicons.eot
jskom/static/fonts/foundicons/social/social_foundicons.svg
