Metadata-Version: 2.1
Name: jskom
Version: 0.26
Summary: Jskom is a web based LysKOM client written in Javascript
Home-page: https://github.com/osks/jskom
Author: Oskar Skoog
Author-email: oskar@osd.se
License: UNKNOWN
Platform: UNKNOWN
Requires-Python: >=3.6
